hnn_utils/__init__.py
hnn_utils/callbacks/__init__.py
hnn_utils/callbacks/ema.py
hnn_utils/datasets/__init__.py
hnn_utils/datasets/guacamol.py
hnn_utils/datasets/utils.py
hnn_utils/datasets/zinc.py
hnn_utils/datasets/vocab/guac.json
hnn_utils/datasets/vocab/guac_random.json
hnn_utils/datasets/vocab/zinc20.json
hnn_utils/nn/ALiBi.py
hnn_utils/nn/RoPE.py
hnn_utils/nn/Transformer.py
hnn_utils/nn/__init__.py
hnn_utils/nn/ffn.py
hnn_utils/nn/functional.py
hnn_utils/nn/normalization.py
hnn_utils-0.3.10.dist-info/METADATA
hnn_utils-0.3.10.dist-info/WHEEL
hnn_utils-0.3.10.dist-info/licenses/LICENSE
hnn_utils-0.3.10.dist-info/RECORD
