Metadata-Version: 2.3
Name: hnn-utils
Version: 0.3.10
Summary: Various utilities used throughout my research
Author-email: Haydn Jones <haydnjonest@gmail.com>
License-File: LICENSE
Requires-Python: >=3.10
Requires-Dist: datasets>=2.19.0
Requires-Dist: einops>=0.7.0
Requires-Dist: lightning>=2.0.0
Requires-Dist: rdkit>=2023.3.1
Requires-Dist: selfies>=2.1.2
